to_parquet_to_aws/__init__.py
to_parquet_to_aws/main.py
to_parquet_to_aws-0.4.dist-info/METADATA
to_parquet_to_aws-0.4.dist-info/WHEEL
to_parquet_to_aws-0.4.dist-info/top_level.txt
to_parquet_to_aws-0.4.dist-info/RECORD
